{"version": 0.6, "generator": "Overpass API 0.7.61.5 4133829e", "osm3s": {"timestamp_osm_base": "2024-02-26T22:13:28Z", "copyright": "The data included in this document is from www.openstreetmap.org. The data is made available under ODbL."}, "elements": [{"type": "node", "id": 1874869293, "lat": -23.3891702, "lon": -48.7238563}, {"type": "node", "id": 1874869984, "lat": -23.3896437, "lon": -48.7235312}, {"type": "node", "id": 1874870102, "lat": -23.3896388, "lon": -48.7235191}, {"type": "node", "id": 1874870189, "lat": -23.3891591, "lon": -48.7238396}, {"type": "node", "id": 8169164351, "lat": -23.3874337, "lon": -48.7268629}, {"type": "node", "id": 8169164352, "lat": -23.3872301, "lon": -48.7270168}, {"type": "node", "id": 8169164353, "lat": -23.3871594, "lon": -48.7270291}, {"type": "node", "id": 8169164354, "lat": -23.3870335, "lon": -48.7268314}, {"type": "node", "id": 8169164355, "lat": -23.3872901, "lon": -48.7266374}, {"type": "way", "id": 177016709, "nodes": [1874869984, 1874870102, 1874870189, 1874869293, 1874869984], "tags": {"amenity": "parking"}}, {"type": "way", "id": 878040697, "nodes": [8169164351, 8169164352, 8169164353, 8169164354, 8169164355, 8169164351], "tags": {"amenity": "hospital", "healthcare": "hospital", "name": "Hospital Municipal Leonardo Van Melis"}}]}